lang_model_cli/__init__.py
lang_model_cli/main.py
lang_model_cli-0.1.6.dist-info/METADATA
lang_model_cli-0.1.6.dist-info/WHEEL
lang_model_cli-0.1.6.dist-info/entry_points.txt
lang_model_cli-0.1.6.dist-info/licenses/LICENSE
lang_model_cli-0.1.6.dist-info/RECORD
